setup.py
dist_prob_g_n/Binomialdistribution.py
dist_prob_g_n/Gaussiandistribution.py
dist_prob_g_n/Generaldistribution.py
dist_prob_g_n/__init__.py
dist_prob_g_n.egg-info/PKG-INFO
dist_prob_g_n.egg-info/SOURCES.txt
dist_prob_g_n.egg-info/dependency_links.txt
dist_prob_g_n.egg-info/not-zip-safe
dist_prob_g_n.egg-info/top_level.txt