Metadata-Version: 1.0
Name: dist-prob-g-n
Version: 1.1
Summary: Gaussian and binomial distributions
Home-page: UNKNOWN
Author: Sayana V
Author-email: UNKNOWN
License: UNKNOWN
Platform: UNKNOWN
